kurveclient/__init__.py
kurveclient/app.py
kurveclient/auth.py
kurveclient/interaction.py
kurveclient/models.py
tests/__init__.py
tests/test_client.py
venv/bin/activate_this.py
venv/bin/find_spark_home.py
venv/bin/jp.py
kurveclient-0.1.5.dist-info/METADATA
kurveclient-0.1.5.dist-info/WHEEL
kurveclient-0.1.5.dist-info/top_level.txt
kurveclient-0.1.5.dist-info/RECORD
